certbot_py/__init__.py
certbot_py/client.py
certbot_py-0.10.1.dist-info/DESCRIPTION.rst
certbot_py-0.10.1.dist-info/METADATA
certbot_py-0.10.1.dist-info/RECORD
certbot_py-0.10.1.dist-info/WHEEL
certbot_py-0.10.1.dist-info/entry_points.txt
certbot_py-0.10.1.dist-info/metadata.json
certbot_py-0.10.1.dist-info/top_level.txt
