Metadata-Version: 2.0
Name: certbot-py
Version: 0.10.1
Summary: Python module to integrate automated Let's Encrypt `certbot certonly` certificate creation into Python projects.
Home-page: https://github.com/jaddison/certbot_py
Author: jaddison
Author-email: addi00+github.com@gmail.com
License: MIT
Keywords: certbot letsencrypt ssl certificate https secure encrypt encryption
Platform: UNKNOWN
Classifier: Development Status :: 3 - Alpha
Classifier: Topic :: Internet :: WWW/HTTP
Classifier: Topic :: Security
Classifier: Environment :: Web Environment
Classifier: Intended Audience :: Developers
Classifier: Intended Audience :: Information Technology
Classifier: License :: OSI Approved :: MIT License
Classifier: Programming Language :: Python :: 2
Classifier: Programming Language :: Python :: 2.6
Classifier: Programming Language :: Python :: 2.7
Classifier: Programming Language :: Python :: 3
Classifier: Programming Language :: Python :: 3.3
Classifier: Programming Language :: Python :: 3.4
Classifier: Programming Language :: Python :: 3.5
Classifier: Programming Language :: Python :: 3.6
Requires-Dist: six
